dota2monitor/__init__.py
dota2monitor/models/__init__.py
dota2monitor/models/backpack.py
dota2monitor/models/dota2_data.py
dota2monitor/models/event.py
dota2monitor/models/event_managed.py
dota2monitor/models/event_manager.py
dota2monitor/models/hero.py
dota2monitor/models/map_info.py
dota2monitor/models/player.py
dota2monitor/models/provider.py
dota2monitor/models/spells.py
dota2monitor/server/__init__.py
dota2monitor/server/dota2monitor.py
dota2monitor-0.0.0.3.dist-info/LICENSE
dota2monitor-0.0.0.3.dist-info/METADATA
dota2monitor-0.0.0.3.dist-info/WHEEL
dota2monitor-0.0.0.3.dist-info/top_level.txt
dota2monitor-0.0.0.3.dist-info/RECORD
