Metadata-Version: 2.1
Name: dota2monitor
Version: 0.0.0.3
Summary: Dota2Monitor allows you to use GameState Integration Monitoring to track events happening in Dota 2 matches.
Author-email: imbalanceinbalance <imbalanceinbalance@gmail.com>
License: MIT License
Project-URL: Homepage, https://github.com/imbalanceinbalance/dota2monitor
Project-URL: Documentation, https://github.com/imbalanceinbalance/dota2monitor
Keywords: dota,gsi
Platform: Linux
Platform: Windows
Classifier: Programming Language :: Python :: 3
Classifier: License :: OSI Approved :: MIT License
Classifier: Operating System :: OS Independent
Requires-Python: >=3.6
License-File: LICENSE
Requires-Dist: Flask >=3.0.0
Requires-Dist: gevent >=21.8.0
